easymobile/__init__.py
easymobile/airtime_api.py
easymobile/base.py
easymobile/cable_api.py
easymobile/client.py
easymobile/data_api.py
easymobile/exceptions.py
easymobile/mocked.py
easymobile/utils.py
easymobile/version.py
easymobile-0.2.0.post0.dist-info/LICENSE
easymobile-0.2.0.post0.dist-info/METADATA
easymobile-0.2.0.post0.dist-info/WHEEL
easymobile-0.2.0.post0.dist-info/top_level.txt
easymobile-0.2.0.post0.dist-info/RECORD
