Metadata-Version: 2.1
Name: easymobile
Version: 0.2.0.post0
Summary: EASYMOBILE Python client library
Author-email: Ephraim <ephraimakolo2017@gmail.com>
License: MIT
Project-URL: homepage, https://github.com/jake-ephraim/EASYMOBILE
Project-URL: repository, https://github.com/jake-ephraim/EASYMOBILE
Keywords: EASYMOBILE,easymobile
Classifier: Topic :: Software Development :: Libraries :: Python Modules
Classifier: Development Status :: 2 - Pre-Alpha
Classifier: Intended Audience :: Developers
Classifier: Natural Language :: English
Requires-Python: <4.0,>=3.7
License-File: LICENSE
Requires-Dist: requests
